[
    {
        "text": "apple\nbanana\ncherry\ndate\nelderberry\nfig\ngrape",
        "description": "Display only the first 3 lines of this fruit list.",
        "expected": "apple\nbanana\ncherry",
        "hint": "Use the head command with -n or just a number"
    },
    {
        "text": "one\ntwo\nthree\nfour\nfive\nsix\nseven",
        "description": "Display the last 3 lines.",
        "expected": "five\nsix\nseven",
        "hint": "Use the tail command with -n or a number"
    },
    {
        "text": "error: file not found\ninfo: starting process\nerror: connection failed\ndebug: checking status\nerror: timeout occurred\ninfo: process complete",
        "description": "Find all lines containing 'error'.",
        "expected": "error: file not found\nerror: connection failed\nerror: timeout occurred",
        "hint": "Use grep with the pattern 'error'"
    },
    {
        "text": "banana\napple\ncherry\napple\ndate\nbanana\napple",
        "description": "Sort these fruits alphabetically.",
        "expected": "apple\napple\napple\nbanana\nbanana\ncherry\ndate",
        "hint": "Use the sort command"
    },
    {
        "text": "5\n3\n8\n1\n9\n2\n7",
        "description": "Sort these numbers in numeric order.",
        "expected": "1\n2\n3\n5\n7\n8\n9",
        "hint": "Use sort -n for numeric sorting"
    },
    {
        "text": "hello world\nthis is a test\nlinux commands are fun\npractice makes perfect",
        "description": "Count the total number of lines.",
        "expected": "4",
        "hint": "Use wc with the -l flag"
    },
    {
        "text": "one two three\nfour five six\nseven eight nine",
        "description": "Count the total number of words.",
        "expected": "9",
        "hint": "Use wc with the -w flag"
    }
]
